[
  {
    "id": "job-demo-001",
    "company": "Northstar Analytics",
    "roleTitle": "Senior Product Analyst",
    "applicationDate": "2026-02-20",
    "status": "Applied",
    "jobUrl": "https://northstar.example/jobs/pa-102",
    "atsUrl": "https://ats.northstar.example/candidate/pa-102",
    "salaryRange": "$120000 - $145000",
    "notes": "Referred by former teammate. Highlight dashboard storytelling work.",
    "contactPerson": "Avery Cole",
    "nextAction": "Send follow-up email",
    "nextActionDueDate": "2026-03-05",
    "createdAt": "2026-02-20T15:45:00.000Z",
    "updatedAt": "2026-02-20T15:45:00.000Z"
  },
  {
    "id": "job-demo-002",
    "company": "Ridgeway Health",
    "roleTitle": "Product Manager, Platform",
    "applicationDate": "2026-02-14",
    "status": "Phone Screen",
    "jobUrl": "https://ridgeway.example/careers/pm-platform",
    "atsUrl": "https://workday.ridgeway.example/applications/pm-platform",
    "salaryRange": "$135000 - $160000",
    "notes": "Phone screen completed, recruiter asked for availability next week.",
    "contactPerson": "Jordan Lee",
    "nextAction": "Share interview availability",
    "nextActionDueDate": "2026-03-04",
    "createdAt": "2026-02-14T10:10:00.000Z",
    "updatedAt": "2026-03-01T18:02:00.000Z"
  },
  {
    "id": "job-demo-003",
    "company": "Atlas Payments",
    "roleTitle": "Staff UX Designer",
    "applicationDate": "2026-01-30",
    "status": "Interview",
    "jobUrl": "https://atlaspay.example/jobs/staff-ux",
    "atsUrl": "https://greenhouse.atlaspay.example/staff-ux",
    "salaryRange": "$150000 - $180000",
    "notes": "Panel interview scheduled. Prepare case study with measurable outcomes.",
    "contactPerson": "Morgan Patel",
    "nextAction": "Panel interview",
    "nextActionDueDate": "2026-03-08",
    "createdAt": "2026-01-30T09:00:00.000Z",
    "updatedAt": "2026-02-28T20:30:00.000Z"
  },
  {
    "id": "job-demo-004",
    "company": "Bluepine Cloud",
    "roleTitle": "Developer Relations Engineer",
    "applicationDate": "2026-02-02",
    "status": "Wishlist",
    "jobUrl": "https://bluepine.example/careers/devrel",
    "atsUrl": "",
    "salaryRange": "$125000 - $150000",
    "notes": "Need to tailor portfolio toward technical writing and workshops.",
    "contactPerson": "",
    "nextAction": "Research team blog and speaking style",
    "nextActionDueDate": "2026-03-12",
    "createdAt": "2026-02-02T13:25:00.000Z",
    "updatedAt": "2026-02-25T07:14:00.000Z"
  },
  {
    "id": "job-demo-005",
    "company": "Sunline Robotics",
    "roleTitle": "Product Operations Manager",
    "applicationDate": "2026-02-18",
    "status": "Offer",
    "jobUrl": "https://sunline.example/jobs/pops",
    "atsUrl": "https://lever.sunline.example/jobs/pops",
    "salaryRange": "$140000 - $165000",
    "notes": "Offer received. Evaluating equity and remote flexibility.",
    "contactPerson": "Riley Gomez",
    "nextAction": "Respond to offer",
    "nextActionDueDate": "2026-03-06",
    "createdAt": "2026-02-18T12:00:00.000Z",
    "updatedAt": "2026-03-03T16:20:00.000Z"
  },
  {
    "id": "job-demo-006",
    "company": "Harbor Bio",
    "roleTitle": "Research Program Coordinator",
    "applicationDate": "2026-01-22",
    "status": "Rejected",
    "jobUrl": "https://harborbio.example/careers/rpc",
    "atsUrl": "",
    "salaryRange": "$90000 - $110000",
    "notes": "Closed after final round. Keep relationship warm for future roles.",
    "contactPerson": "Dana Kim",
    "nextAction": "Send thank-you note",
    "nextActionDueDate": "2026-02-01",
    "createdAt": "2026-01-22T11:12:00.000Z",
    "updatedAt": "2026-02-01T09:00:00.000Z"
  },
  {
    "id": "job-demo-007",
    "company": "Cinder Labs",
    "roleTitle": "Senior Frontend Engineer",
    "applicationDate": "2026-02-28",
    "status": "Applied",
    "jobUrl": "https://cinder.example/jobs/sfe",
    "atsUrl": "https://ashby.cinder.example/sfe",
    "salaryRange": "$145000 - $175000",
    "notes": "Applied with referral from meetup contact.",
    "contactPerson": "Kai Bennett",
    "nextAction": "Ping recruiter on LinkedIn",
    "nextActionDueDate": "2026-03-10",
    "createdAt": "2026-02-28T22:02:00.000Z",
    "updatedAt": "2026-02-28T22:02:00.000Z"
  },
  {
    "id": "job-demo-008",
    "company": "Fieldnote AI",
    "roleTitle": "ML Product Specialist",
    "applicationDate": "2026-02-07",
    "status": "Withdrawn",
    "jobUrl": "https://fieldnote.example/jobs/mlps",
    "atsUrl": "",
    "salaryRange": "$130000 - $150000",
    "notes": "Withdrew due to in-office requirement.",
    "contactPerson": "Samir Rao",
    "nextAction": "Archive application",
    "nextActionDueDate": "2026-02-12",
    "createdAt": "2026-02-07T08:55:00.000Z",
    "updatedAt": "2026-02-12T14:40:00.000Z"
  },
  {
    "id": "job-demo-009",
    "company": "Ironwood Commerce",
    "roleTitle": "Growth Marketing Manager",
    "applicationDate": "2026-01-25",
    "status": "Interview",
    "jobUrl": "https://ironwood.example/careers/gmm",
    "atsUrl": "https://jobs.ironwood.example/gmm",
    "salaryRange": "$115000 - $140000",
    "notes": "Case interview includes CAC payback exercise.",
    "contactPerson": "Priya Shah",
    "nextAction": "Submit case study",
    "nextActionDueDate": "2026-03-02",
    "createdAt": "2026-01-25T18:33:00.000Z",
    "updatedAt": "2026-03-01T12:05:00.000Z"
  },
  {
    "id": "job-demo-010",
    "company": "Mariner Security",
    "roleTitle": "Technical Program Manager",
    "applicationDate": "2026-02-11",
    "status": "Phone Screen",
    "jobUrl": "https://mariner.example/jobs/tpm",
    "atsUrl": "https://greenhouse.mariner.example/tpm",
    "salaryRange": "$155000 - $185000",
    "notes": "Recruiter requested examples of incident response coordination.",
    "contactPerson": "Nora Diaz",
    "nextAction": "Prepare STAR stories",
    "nextActionDueDate": "2026-03-01",
    "createdAt": "2026-02-11T05:15:00.000Z",
    "updatedAt": "2026-02-27T19:44:00.000Z"
  },
  {
    "id": "job-demo-011",
    "company": "Aperture Logistics",
    "roleTitle": "Data Engineer",
    "applicationDate": "2026-01-17",
    "status": "Applied",
    "jobUrl": "https://aperture.example/jobs/data-engineer",
    "atsUrl": "",
    "salaryRange": "$128000 - $152000",
    "notes": "No response yet. Follow up after 3 weeks.",
    "contactPerson": "",
    "nextAction": "Check in with recruiting",
    "nextActionDueDate": "2026-02-20",
    "createdAt": "2026-01-17T16:41:00.000Z",
    "updatedAt": "2026-02-20T09:25:00.000Z"
  },
  {
    "id": "job-demo-012",
    "company": "Lumen Education",
    "roleTitle": "Customer Success Lead",
    "applicationDate": "2026-02-23",
    "status": "Wishlist",
    "jobUrl": "https://lumen.example/careers/csl",
    "atsUrl": "",
    "salaryRange": "$95000 - $120000",
    "notes": "Need to connect with former CSM at company before applying.",
    "contactPerson": "Casey White",
    "nextAction": "Reach out for informational chat",
    "nextActionDueDate": "2026-03-11",
    "createdAt": "2026-02-23T21:05:00.000Z",
    "updatedAt": "2026-02-23T21:05:00.000Z"
  }
]
